MANIFEST.in
pyproject.toml
setup.cfg
setup.py
django_seo_plus/__init__.py
django_seo_plus/admin.py
django_seo_plus/apps.py
django_seo_plus/meta.py
django_seo_plus/models.py
django_seo_plus/tests.py
django_seo_plus/views.py
django_seo_plus.egg-info/PKG-INFO
django_seo_plus.egg-info/SOURCES.txt
django_seo_plus.egg-info/dependency_links.txt
django_seo_plus.egg-info/requires.txt
django_seo_plus.egg-info/top_level.txt
django_seo_plus/migrations/__init__.py
django_seo_plus/templates/django_seo_plus/meta.html